clilib/__init__.py
clilib/events.py
clilib/builders/__init__.py
clilib/builders/app.py
clilib/builders/spec.py
clilib/config/__init__.py
clilib/config/config.py
clilib/config/config_loader.py
clilib/util/__init__.py
clilib/util/arg_tools.py
clilib/util/decorators.py
clilib/util/dict.py
clilib/util/errors.py
clilib/util/loader.py
clilib/util/logging.py
clilib/util/text.py
clilib/util/util.py
clilib/util/wheel.py
clilib-3.7.4.dist-info/LICENSE
clilib-3.7.4.dist-info/METADATA
clilib-3.7.4.dist-info/WHEEL
clilib-3.7.4.dist-info/entry_points.txt
clilib-3.7.4.dist-info/top_level.txt
clilib-3.7.4.dist-info/RECORD
